setup.py
continuate/__init__.py
continuate/krylov.py
continuate/logger.py
continuate/newton.py
continuate/qr.py
continuate/single_parameter.py
continuate/test_krylov.py
continuate/test_newton.py
continuate.egg-info/PKG-INFO
continuate.egg-info/SOURCES.txt
continuate.egg-info/dependency_links.txt
continuate.egg-info/top_level.txt