Metadata-Version: 1.0
Name: continuate
Version: 0.2.1
Summary: parameter continuation of continuous function
Home-page: http://github.com/termoshtt/continuate
Author: Toshiki Teramura
Author-email: toshiki.teramura+continuate@gmail.com
License: MIT
Keywords: science
Platform: UNKNOWN
